transcal/BJT.py
transcal/JFET.py
transcal/MOSFET.py
transcal/__init__.py
transcal/errors.py
transcal-1.0.0.dist-info/METADATA
transcal-1.0.0.dist-info/WHEEL
transcal-1.0.0.dist-info/licenses/LICENSE
transcal-1.0.0.dist-info/RECORD
