Metadata-Version: 2.1
Name: transcal
Version: 1.0.0
Summary: 'transcal' is a package which contain the transistor analyzes
Project-URL: Homepage, https://github.com/CanGulmez/transcal
Author-email: Can Gulmez <ahmetcangulmez02@gmail.com>
License-File: LICENSE
Keywords: electornics, transistors
Classifier: License :: OSI Approved :: MIT License
Classifier: Operating System :: OS Independent
Classifier: Programming Language :: Python :: 3
Requires-Python: >=3.8
